{
  "db_name": "SQLite",
  "query": "SELECT id as \"id: i32\", title, file_path as \"path\", html from presentations",
  "describe": {
    "columns": [
      {
        "name": "id: i32",
        "ordinal": 0,
        "type_info": "Integer"
      },
      {
        "name": "title",
        "ordinal": 1,
        "type_info": "Text"
      },
      {
        "name": "path",
        "ordinal": 2,
        "type_info": "Text"
      },
      {
        "name": "html",
        "ordinal": 3,
        "type_info": "Bool"
      }
    ],
    "parameters": {
      "Right": 0
    },
    "nullable": [
      false,
      false,
      false,
      false
    ]
  },
  "hash": "7ace613c138f874198ea8e5f72697d4c604fe7b755fdcb6773692c813b5e1d4b"
}
